{
    "mAniA": {
        "current_rating": 1024,
        "highest_rating": 1024,
        "lowest_rating": 1000,
        "base_rating": 1000,
        "matches_played": 3,
        "wins": 3,
        "losses": 0,
        "matchesList": {
            "39489303062308": "W",
            "41688183904221": "W"
        }
    },
    "Baji": {
        "current_rating": 918,
        "highest_rating": 948,
        "lowest_rating": 900,
        "base_rating": 900,
        "matches_played": 13,
        "wins": 4,
        "losses": 9,
        "matchesList": {
            "39489303062308": "L",
            "41688183904221": "L",
            "25032388340691": "W",
            "29992602867295": "W",
            "60823556026671": "L",
            "49165087841854": "L"
        }
    },
    "Karma": {
        "current_rating": 888,
        "highest_rating": 900,
        "lowest_rating": 858,
        "base_rating": 900,
        "matches_played": 19,
        "wins": 11,
        "losses": 8,
        "matchesList": {
            "72809569186051": "L",
            "63802188612238": "L",
            "55103162042188": "W",
            "19303155184793": "L",
            "40122721469070": "W",
            "67409177064796": "W",
            "66599589449489": "W",
            "44918248946158": "W",
            "5918722429921": "W"
        }
    },
    "Dexter": {
        "current_rating": 850,
        "highest_rating": 886,
        "lowest_rating": 844,
        "base_rating": 850,
        "matches_played": 25,
        "wins": 10,
        "losses": 15,
        "matchesList": {
            "72809569186051": "W",
            "63802188612238": "W",
            "40122721469070": "L",
            "67409177064796": "L",
            "66599589449489": "L",
            "44918248946158": "L",
            "25032388340691": "L",
            "29992602867295": "L",
            "60823556026671": "L",
            "49165087841854": "W"
        }
    },
    "Dee LK": {
        "current_rating": 832,
        "highest_rating": 850,
        "lowest_rating": 796,
        "base_rating": 820,
        "matches_played": 25,
        "wins": 12,
        "losses": 13,
        "matchesList": {
            "72809569186051": "L",
            "63802188612238": "W",
            "55103162042188": "L",
            "19303155184793": "W",
            "40122721469070": "W",
            "67409177064796": "W",
            "66599589449489": "L",
            "44918248946158": "L",
            "25032388340691": "L",
            "49165087841854": "W",
            "50850864734454": "W",
            "5918722429921": "L"
        }
    },
    "Immortal": {
        "current_rating": 869,
        "highest_rating": 875,
        "lowest_rating": 827,
        "base_rating": 875,
        "matches_played": 20,
        "wins": 13,
        "losses": 7,
        "matchesList": {
            "39489303062308": "W",
            "41688183904221": "L",
            "72809569186051": "W",
            "63802188612238": "L",
            "55103162042188": "W",
            "40122721469070": "W",
            "67409177064796": "W",
            "66599589449489": "W",
            "50850864734454": "L"
        }
    },
    "Zxc": {
        "current_rating": 818,
        "highest_rating": 830,
        "lowest_rating": 818,
        "base_rating": 830,
        "matches_played": 0,
        "wins": 0,
        "losses": 0,
        "matchesList": {}
    },
    "@jey@2": {
        "current_rating": 808,
        "highest_rating": 850,
        "lowest_rating": 766,
        "base_rating": 850,
        "matches_played": 12,
        "wins": 6,
        "losses": 6,
        "matchesList": {
            "44918248946158": "W",
            "25032388340691": "W",
            "29992602867295": "W",
            "60823556026671": "W",
            "49165087841854": "L"
        }
    },
    "2Kminus": {
        "current_rating": 762,
        "highest_rating": 762,
        "lowest_rating": 750,
        "base_rating": 750,
        "matches_played": 8,
        "wins": 5,
        "losses": 3,
        "matchesList": {
            "72809569186051": "W",
            "19303155184793": "L",
            "44918248946158": "W",
            "25032388340691": "L",
            "29992602867295": "W",
            "60823556026671": "W",
            "50850864734454": "L",
            "5918722429921": "W"
        }
    },
    "Addy": {
        "current_rating": 743,
        "highest_rating": 749,
        "lowest_rating": 725,
        "base_rating": 725,
        "matches_played": 5,
        "wins": 2,
        "losses": 3,
        "matchesList": {
            "40122721469070": "L",
            "67409177064796": "L",
            "66599589449489": "W"
        }
    },
    "White Eagle": {
        "current_rating": 743,
        "highest_rating": 785,
        "lowest_rating": 725,
        "base_rating": 725,
        "matches_played": 0,
        "wins": 0,
        "losses": 0,
        "matchesList": {}
    },
    "Kallu": {
        "current_rating": 726,
        "highest_rating": 750,
        "lowest_rating": 720,
        "base_rating": 750,
        "matches_played": 1,
        "wins": 1,
        "losses": 0,
        "matchesList": {}
    },
    "Ghatak": {
        "current_rating": 722,
        "highest_rating": 728,
        "lowest_rating": 650,
        "base_rating": 650,
        "matches_played": 18,
        "wins": 11,
        "losses": 7,
        "matchesList": {
            "39489303062308": "W",
            "41688183904221": "W",
            "72809569186051": "L",
            "63802188612238": "L",
            "55103162042188": "L",
            "19303155184793": "W",
            "44918248946158": "L",
            "25032388340691": "W",
            "29992602867295": "L",
            "60823556026671": "W",
            "49165087841854": "W",
            "50850864734454": "W",
            "5918722429921": "L"
        }
    },
    "Endless": {
        "current_rating": 692,
        "highest_rating": 704,
        "lowest_rating": 680,
        "base_rating": 680,
        "matches_played": 6,
        "wins": 3,
        "losses": 3,
        "matchesList": {
            "39489303062308": "L",
            "41688183904221": "W",
            "29992602867295": "L",
            "60823556026671": "L"
        }
    },
    "Axiom": {
        "current_rating": 700,
        "highest_rating": 700,
        "lowest_rating": 682,
        "base_rating": 700,
        "matches_played": 4,
        "wins": 3,
        "losses": 1,
        "matchesList": {
            "72809569186051": "L",
            "63802188612238": "W",
            "44918248946158": "W",
            "25032388340691": "W"
        }
    },
    "Varad": {
        "current_rating": 658,
        "highest_rating": 718,
        "lowest_rating": 658,
        "base_rating": 700,
        "matches_played": 27,
        "wins": 11,
        "losses": 16,
        "matchesList": {
            "39489303062308": "L",
            "41688183904221": "L",
            "55103162042188": "L",
            "19303155184793": "L",
            "40122721469070": "L",
            "67409177064796": "L",
            "66599589449489": "L",
            "44918248946158": "L",
            "25032388340691": "L",
            "29992602867295": "L"
        }
    },
    "Mabba": {
        "current_rating": 674,
        "highest_rating": 680,
        "lowest_rating": 650,
        "base_rating": 650,
        "matches_played": 13,
        "wins": 8,
        "losses": 5,
        "matchesList": {
            "60823556026671": "W",
            "49165087841854": "L",
            "50850864734454": "W",
            "5918722429921": "W"
        }
    },
    "Ojas": {
        "current_rating": 644,
        "highest_rating": 668,
        "lowest_rating": 602,
        "base_rating": 650,
        "matches_played": 12,
        "wins": 6,
        "losses": 6,
        "matchesList": {
            "72809569186051": "W",
            "63802188612238": "W",
            "55103162042188": "W",
            "19303155184793": "W",
            "40122721469070": "L",
            "67409177064796": "L",
            "66599589449489": "L",
            "5918722429921": "L"
        }
    },
    "Ship": {
        "current_rating": 606,
        "highest_rating": 648,
        "lowest_rating": 594,
        "base_rating": 600,
        "matches_played": 18,
        "wins": 6,
        "losses": 12,
        "matchesList": {
            "39489303062308": "L",
            "41688183904221": "W",
            "63802188612238": "L",
            "55103162042188": "L",
            "19303155184793": "W",
            "66599589449489": "W"
        }
    },
    "Outlier": {
        "current_rating": 614,
        "highest_rating": 650,
        "lowest_rating": 614,
        "base_rating": 650,
        "matches_played": 4,
        "wins": 1,
        "losses": 3,
        "matchesList": {
            "50850864734454": "L",
            "5918722429921": "L"
        }
    },
    "Salazar": {
        "current_rating": 558,
        "highest_rating": 558,
        "lowest_rating": 540,
        "base_rating": 550,
        "matches_played": 18,
        "wins": 10,
        "losses": 8,
        "matchesList": {}
    },
    "Auror": {
        "current_rating": 544,
        "highest_rating": 550,
        "lowest_rating": 532,
        "base_rating": 550,
        "matches_played": 3,
        "wins": 2,
        "losses": 1,
        "matchesList": {}
    },
    "Gautami": {
        "current_rating": 476,
        "highest_rating": 506,
        "lowest_rating": 464,
        "base_rating": 500,
        "matches_played": 21,
        "wins": 8,
        "losses": 13,
        "matchesList": {
            "55103162042188": "W",
            "19303155184793": "L",
            "40122721469070": "W",
            "67409177064796": "W",
            "29992602867295": "W",
            "60823556026671": "L",
            "50850864734454": "L"
        }
    },
    "Mateesh": {
        "current_rating": 554,
        "highest_rating": 554,
        "lowest_rating": 376,
        "base_rating": 500,
        "matches_played": 13,
        "wins": 8,
        "losses": 5,
        "matchesList": {
            "39489303062308": "W",
            "41688183904221": "L",
            "50850864734454": "W",
            "5918722429921": "W"
        }
    }
}